notizen/__init__.py
notizen/cli.py
notizen/file_processing.py
notizen/helpers.py
notizen/indices.py
notizen/updatedb.py
notizen-1.0.0.dist-info/DESCRIPTION.rst
notizen-1.0.0.dist-info/METADATA
notizen-1.0.0.dist-info/RECORD
notizen-1.0.0.dist-info/WHEEL
notizen-1.0.0.dist-info/entry_points.txt
notizen-1.0.0.dist-info/metadata.json
notizen-1.0.0.dist-info/top_level.txt
notizen-1.0.0.dist-info/zip-safe
